__init__.py
elucidoc/__init__.py
elucidoc/__main__.py
elucidoc/accessory.py
elucidoc/eluciDoc.py
elucidoc-2024.7.24.dist-info/LICENSE.txt
elucidoc-2024.7.24.dist-info/METADATA
elucidoc-2024.7.24.dist-info/WHEEL
elucidoc-2024.7.24.dist-info/top_level.txt
elucidoc-2024.7.24.dist-info/RECORD
