Metadata-Version: 2.1
Name: elucidoc
Version: 2024.7.24
Summary: Screens legal and other texts for sentences and clauses containing user defined search phrases
Author: John Blake
Author-email: elucidoc535@gmail.com
License: Copyright 2023 John R. Blake, Jr.
Project-URL: Source Code, https://github.com/jblake1965/eluciDoc
Project-URL: License, https://github.com/jblake1965/eluciDoc/blob/developer/LICENSE.txt
Keywords: legal,text,analysis
Classifier: Programming Language :: Python
Classifier: Programming Language :: Python :: 3
Classifier: License :: Other/Proprietary License
License-File: LICENSE.txt
Requires-Dist: docx2python ==2.10.1
Requires-Dist: openpyxl ==3.1.5
Requires-Dist: pandas ==2.2.2
Requires-Dist: pdfminer.six ==20240706
Requires-Dist: python-docx ==1.1.2
Requires-Dist: rich ==13.7.1
Requires-Dist: spacy ==3.7.5
Requires-Dist: textacy ==0.13.0
